{"errors":[],"warnings":[],"namedChunkGroups":{"app":{"chunks":[6,2],"assets":["webpack-runtime-8dcec661153bbfb49751.js","webpack-runtime-8dcec661153bbfb49751.js.map","app-c9b7b53fc2d2a31861df.js","app-c9b7b53fc2d2a31861df.js.map"],"children":{},"childAssets":{}},"component---src-pages-404-js":{"chunks":[0,1,3],"assets":["styles.55f08223f1f21b432b49.css","styles-a3fa757d318e345a27e1.js","styles-a3fa757d318e345a27e1.js.map","1-e3506df48c6d488bd55a.js","1-e3506df48c6d488bd55a.js.map","component---src-pages-404-js-7cf0210f1b2c352554e8.js","component---src-pages-404-js-7cf0210f1b2c352554e8.js.map"],"children":{},"childAssets":{}},"component---src-pages-contact-js":{"chunks":[0,1,4],"assets":["styles.55f08223f1f21b432b49.css","styles-a3fa757d318e345a27e1.js","styles-a3fa757d318e345a27e1.js.map","1-e3506df48c6d488bd55a.js","1-e3506df48c6d488bd55a.js.map","component---src-pages-contact-js-9d2064a5b458dffd62aa.js","component---src-pages-contact-js-9d2064a5b458dffd62aa.js.map"],"children":{},"childAssets":{}},"component---src-pages-index-js":{"chunks":[0,1,7,5],"assets":["styles.55f08223f1f21b432b49.css","styles-a3fa757d318e345a27e1.js","styles-a3fa757d318e345a27e1.js.map","1-e3506df48c6d488bd55a.js","1-e3506df48c6d488bd55a.js.map","7-0d827139c64e8d769668.js","7-0d827139c64e8d769668.js.map","component---src-pages-index-js-add8e17a140a6bd4b4d9.js","component---src-pages-index-js-add8e17a140a6bd4b4d9.js.map"],"children":{},"childAssets":{}}},"assetsByChunkName":{"app":["webpack-runtime-8dcec661153bbfb49751.js","app-c9b7b53fc2d2a31861df.js"],"component---src-pages-404-js":["styles.55f08223f1f21b432b49.css","styles-a3fa757d318e345a27e1.js","1-e3506df48c6d488bd55a.js","component---src-pages-404-js-7cf0210f1b2c352554e8.js"],"component---src-pages-contact-js":["styles.55f08223f1f21b432b49.css","styles-a3fa757d318e345a27e1.js","1-e3506df48c6d488bd55a.js","component---src-pages-contact-js-9d2064a5b458dffd62aa.js"],"component---src-pages-index-js":["styles.55f08223f1f21b432b49.css","styles-a3fa757d318e345a27e1.js","1-e3506df48c6d488bd55a.js","7-0d827139c64e8d769668.js","component---src-pages-index-js-add8e17a140a6bd4b4d9.js"]}}